nuee/__init__.py
nuee/composition/__init__.py
nuee/data/BCI.csv
nuee/data/BCI.env.csv
nuee/data/__init__.py
nuee/data/dune.csv
nuee/data/dune.env.csv
nuee/data/dune.taxon.csv
nuee/data/mite.csv
nuee/data/mite.env.csv
nuee/data/mite.pcnm.csv
nuee/data/mite.xy.csv
nuee/data/pyrifos.csv
nuee/data/sipoo.csv
nuee/data/sipoo.map.csv
nuee/data/varechem.csv
nuee/data/varespec.csv
nuee/datasets/__init__.py
nuee/datasets/sample_data.py
nuee/dissimilarity/__init__.py
nuee/dissimilarity/anosim.py
nuee/dissimilarity/betadisper.py
nuee/dissimilarity/distances.py
nuee/dissimilarity/mantel.py
nuee/dissimilarity/mrpp.py
nuee/dissimilarity/protest.py
nuee/diversity/__init__.py
nuee/diversity/accumulation.py
nuee/diversity/base.py
nuee/diversity/diversity.py
nuee/diversity/rarefaction.py
nuee/ordination/__init__.py
nuee/ordination/base.py
nuee/ordination/cca.py
nuee/ordination/envfit.py
nuee/ordination/nmds.py
nuee/ordination/ordistep.py
nuee/ordination/pca.py
nuee/ordination/procrustes.py
nuee/ordination/rda.py
nuee/permutation/__init__.py
nuee/permutation/anova.py
nuee/permutation/permanova.py
nuee/permutation/permtest.py
nuee/plotting/__init__.py
nuee/plotting/dissimilarity_plots.py
nuee/plotting/diversity_plots.py
nuee/plotting/ordination_plots.py
nuee-0.1.6.dist-info/licenses/LICENSE
nuee-0.1.6.dist-info/METADATA
nuee-0.1.6.dist-info/WHEEL
nuee-0.1.6.dist-info/top_level.txt
nuee-0.1.6.dist-info/RECORD
