Metadata-Version: 2.4
Name: nuee
Version: 0.1.6
Summary: Community Ecology Analysis in Python
Author: nuee Development Team
License: MIT
Classifier: Development Status :: 3 - Alpha
Classifier: Intended Audience :: Science/Research
Classifier: Operating System :: OS Independent
Classifier: Programming Language :: Python :: 3
Classifier: Programming Language :: Python :: 3.8
Classifier: Programming Language :: Python :: 3.9
Classifier: Programming Language :: Python :: 3.10
Classifier: Programming Language :: Python :: 3.11
Classifier: Topic :: Scientific/Engineering :: Bio-Informatics
Requires-Python: >=3.8
License-File: LICENSE
Requires-Dist: numpy>=1.20.0
Requires-Dist: scipy>=1.7.0
Requires-Dist: pandas>=1.3.0
Requires-Dist: matplotlib>=3.4.0
Requires-Dist: seaborn>=0.11.0
Requires-Dist: scikit-learn>=1.0.0
Requires-Dist: patsy>=0.5.0
Requires-Dist: statsmodels>=0.12.0
Requires-Dist: pytest>=8.3.5
Dynamic: license-file
